movie_barcode/__init__.py
movie_barcode/barcode.py
movie_barcode/movie.py
movie_barcode/movies.py
movie_barcode/timer.py
movie_barcode-1.1.2.dist-info/LICENSE.txt
movie_barcode-1.1.2.dist-info/METADATA
movie_barcode-1.1.2.dist-info/WHEEL
movie_barcode-1.1.2.dist-info/top_level.txt
movie_barcode-1.1.2.dist-info/RECORD
