Metadata-Version: 2.1
Name: movie-barcode
Version: 1.1.2
Summary: A tool to create barcodes for movies using different sorting functions.
Author: Marc Bresson
Author-email: marco.bresson@gmail.com
License: License :: OSI Approved :: European Union Public Licence 1.2 (EUPL 1.2)
Project-URL: Bug Tracker, https://github.com/MarcBresson/movie-barcode/issues
Project-URL: Profil, https://github.com/MarcBresson/
Project-URL: Source, https://github.com/MarcBresson/movie-barcode
Platform: UNKNOWN
Requires-Python: >=3.7
License-File: LICENSE.txt
Requires-Dist: av
Requires-Dist: Pillow
